coinmarketcap/__init__.py
coinmarketcap/coinmarketcap.py
coinmarketcap/utils.py
py_coinmarketcap_client-1.0.0.dist-info/LICENSE
py_coinmarketcap_client-1.0.0.dist-info/METADATA
py_coinmarketcap_client-1.0.0.dist-info/WHEEL
py_coinmarketcap_client-1.0.0.dist-info/top_level.txt
py_coinmarketcap_client-1.0.0.dist-info/RECORD
