Metadata-Version: 2.1
Name: py-coinmarketcap-client
Version: 1.0.0
Summary: CoinMarketCap API wrapper
Home-page: https://github.com/nlnsaoadc/py-coinmarketcap
Author: nlnsaoadc
License: MIT
Platform: UNKNOWN
Classifier: License :: OSI Approved :: MIT License
Classifier: Programming Language :: Python :: 3
Classifier: Programming Language :: Python :: 3.7
License-File: LICENSE
Requires-Dist: requests
